[
  {
    "id": 1,
    "src": "bohemian-man-with-his-arms-crossed.jpg",
    "name": "Yossi Cohen",
    "description": "A good friend of mine"
  },
  {
    "id": 2,
    "src": "young-bearded-man-with-striped-shirt.jpg",
    "name": "Ruth Levi",
    "description": "Math teacher"
  },
  {
    "id": 3,
    "src": "OC3I520.jpg",
    "name": "Dani Israeli",
    "description": "Hardworking student"
  },
  {
    "id": 4,
    "src": "OC3I520.jpg",
    "name": "Dani Israeli",
    "description": "Hardworking student"
  },
  {
    "id": 5,
    "src": "OC3I520.jpg",
    "name": "Dani Israeli",
    "description": "Hardworking student"
  },
  {
    "id": 6,
    "src": "OC3I520.jpg",
    "name": "Dani Israeli",
    "description": "Hardworking student"
  },
  {
    "id": 7,
    "src": "OC3I520.jpg",
    "name": "Dani Israeli",
    "description": "Hardworking student"
  },
  {
    "id": 8,
    "src": "young-bearded-man-with-striped-shirt.jpg",
    "name": "Ruth Levi",
    "description": "Math teacher",
    "date": "Tue Sep 09 2025 09:04:53 GMT+0300 (שעון ישראל (קיץ))"
  },
  {
    "id": 9,
    "src": "young-bearded-man-with-striped-shirt.jpg",
    "name": "Nftali berger",
    "description": "programmer",
    "date": "Tue Sep 09 2025 09:12:19 GMT+0300 (שעון ישראל (קיץ))"
  },
  {
    "id": 10,
    "src": "young-bearded-man-with-striped-shirt.jpg",
    "name": "Nftali",
    "description": "programmer",
    "date": "Tue Sep 09 2025 11:04:39 GMT+0300 (שעון ישראל (קיץ))"
  },
  {
    "id": 11,
    "src": "young-bearded-man-with-striped-shirt.jpg",
    "name": "Nftali berger",
    "description": "programmer",
    "date": "Tue Sep 09 2025 09:27:49 GMT+0300 (שעון ישראל (קיץ))"
  },
  {
    "id": 12,
    "src": "young-bearded-man-with-striped-shirt.jpg",
    "name": "Nftali berger",
    "description": "programmer",
    "date": "Tue Sep 09 2025 09:29:29 GMT+0300 (שעון ישראל (קיץ))"
  },
  {
    "id": 13,
    "src": "young-bearded-man-with-striped-shirt.jpg",
    "name": "Nftali berger",
    "description": "programmer",
    "date": "Tue Sep 09 2025 09:31:30 GMT+0300 (שעון ישראל (קיץ))"
  }
]